{
	"name":"Store",
	"file":{
		"path":"app/Store.js",
		"version":"0.1",
		"author":"zhang_7150@163.com",
		"description":"extend [link=localstoragebase]LocalStorageBase[/link]，对set、get、remove做了扩展，支持递归数据保存和读取",
		"updatetime":"2015-11-25"
	},
	"apis":{
		"Members":{
			"key":{
				"qualifier":"",
				"arguments":"",
				"returnType":"string",
				"description":"缓存的Key"
			},
			"expires":{
				"qualifier":"",
				"arguments":"",
				"default":"1M",
				"returnType":"string",
				"description":"缓存的有效期,y:年,M:月,d:日,h:时,m:分,s:秒"
			}
		},
		"Instance Methods":{
			"set":{
				"qualifier":"",
				"arguments":"(subKey,item)",
				"returnType":"",
				"description":"将item写入本地缓存，如果subKey不为string类型，将忽略item参数并使用父类的set进行操作",
				"parameters":{
					"subKey":{
						"type":"string",
						"description":"子Key"
					},
					"item":{
						"type":"Object",
						"description":"写入本地缓存的对象，支持任意类型"
					}
				}
			},
			"get":{
				"qualifier":"",
				"arguments":"(subKey)",
				"returnType":"Object",
				"description":"根据指定的子key读取本地缓存，如果subKey为空，则使用父类的get返回本地所有缓存",
				"parameters":{
					"subKey":{
						"type":"string",
						"description":"子Key"
					}
				}
			},
			"remove":{
				"qualifier":"",
				"arguments":"(subKey)",
				"returnType":"",
				"description":"根据指定的子key清空缓存，如果subKey为空，则使用父类的remove删除本地所有缓存",
				"parameters":{
					"subKey":{
						"type":"string",
						"description":"子Key"
					}
				}
			}
		},
		"Methods":{
			"instance":{
				"qualifier":"static",
				"arguments":"()",
				"returnType":"",
				"description":"单例模式，用于获取类的唯一实例",
				"parameters":null
			},
			"extend":{
				"qualifier":"static",
				"arguments":"(prototype,staticProps)",
				"returnType":"Store",
				"description":"用于继承产生子类",
				"parameters":{
					"prototype":{
						"type":"Object",
						"description":"原型"
					},
					"staticProps":{
						"type":"Object",
						"description":"静态属性"
					}
				}
			}
		}
	},
	"example":{
		"type":"javascript",
		"path":"store.js"
	}
}